py_ri_ufsc/__init__.py
py_ri_ufsc/config.py
py_ri_ufsc/main.py
py_ri_ufsc/common/for_strings.py
py_ri_ufsc/etl/extraction/__init__.py
py_ri_ufsc/etl/extraction/courses_info/__init__.py
py_ri_ufsc/etl/extraction/courses_info/courses_ufsc.py
py_ri_ufsc/etl/extraction/courses_info/utils.py
py_ri_ufsc/etl/transform_and_load/__init__.py
py_ri_ufsc/etl/transform_and_load/main.py
py_ri_ufsc/etl/transform_and_load/utils.py
py_ri_ufsc/get_metadata/__init__.py
py_ri_ufsc/get_metadata/filters.py
py_ri_ufsc/get_metadata/main.py
py_ri_ufsc/get_metadata/tests.py
py_ri_ufsc/get_metadata/utils.py
py_ri_ufsc-0.9.dist-info/licenses/LICENSE
py_ri_ufsc-0.9.dist-info/METADATA
py_ri_ufsc-0.9.dist-info/WHEEL
py_ri_ufsc-0.9.dist-info/top_level.txt
py_ri_ufsc-0.9.dist-info/RECORD
