Metadata-Version: 2.4
Name: py_ri_ufsc
Version: 0.9
Summary: Program designed to handle searches in metadata stored in UFSC Institutional Repository
Author: Igor Caetano de Souza
Author-email: igorcaetanods@gmail.com
Project-URL: GitHub Repository, https://github.com/IgorCaetano/py_ri_ufsc
Classifier: Programming Language :: Python :: 3
Classifier: Operating System :: OS Independent
Requires-Python: >=3.7
License-File: LICENSE
Requires-Dist: ftfy==6.3.1
Requires-Dist: pandas==2.3.0
Requires-Dist: pyarrow==20.0.0
Requires-Dist: pooch==1.8.2
Requires-Dist: tqdm==4.67.1
Requires-Dist: ipykernel==6.29.5
Requires-Dist: beautifulsoup4==4.13.4
Requires-Dist: requests==2.32.4
Requires-Dist: lxml==5.4.0
Requires-Dist: br-gender==0.1.0
Dynamic: author
Dynamic: author-email
Dynamic: classifier
Dynamic: description
Dynamic: description-content-type
Dynamic: license-file
Dynamic: project-url
Dynamic: requires-dist
Dynamic: requires-python
Dynamic: summary
